gros_client/__init__.py
gros_client/demo.py
gros_client-1.1.21.dist-info/LICENSE
gros_client-1.1.21.dist-info/METADATA
gros_client-1.1.21.dist-info/WHEEL
gros_client-1.1.21.dist-info/top_level.txt
gros_client-1.1.21.dist-info/RECORD
