Metadata-Version: 2.1
Name: gros-client
Version: 1.1.21
Summary: Fourier General Robotics OS - Client Library (python)
Author-email: jax <ming.li@fftai.com>
License: MIT
Project-URL: Homepage, https://github.com/FFTAI/gros_client_py
Project-URL: Bug Tracker, https://github.com/FFTAI/gros_client_py/issues
Project-URL: Blog, https://fftai.github.io/
Classifier: Programming Language :: Python :: 3.10
Classifier: License :: OSI Approved :: MIT License
Classifier: Operating System :: OS Independent
Requires-Python: >=3.10
License-File: LICENSE
Requires-Dist: requests >=2.31.0
Requires-Dist: websocket-client >=1.6.2
